LICENSE
MANIFEST.in
index.html
readme.org
setup.py
.eggs/Pillow-5.3.0-py3.6-linux-x86_64.egg/PIL/BdfFontFile.py
.eggs/Pillow-5.3.0-py3.6-linux-x86_64.egg/PIL/BlpImagePlugin.py
.eggs/Pillow-5.3.0-py3.6-linux-x86_64.egg/PIL/BmpImagePlugin.py
.eggs/Pillow-5.3.0-py3.6-linux-x86_64.egg/PIL/BufrStubImagePlugin.py
.eggs/Pillow-5.3.0-py3.6-linux-x86_64.egg/PIL/ContainerIO.py
.eggs/Pillow-5.3.0-py3.6-linux-x86_64.egg/PIL/CurImagePlugin.py
.eggs/Pillow-5.3.0-py3.6-linux-x86_64.egg/PIL/DcxImagePlugin.py
.eggs/Pillow-5.3.0-py3.6-linux-x86_64.egg/PIL/DdsImagePlugin.py
.eggs/Pillow-5.3.0-py3.6-linux-x86_64.egg/PIL/EpsImagePlugin.py
.eggs/Pillow-5.3.0-py3.6-linux-x86_64.egg/PIL/ExifTags.py
.eggs/Pillow-5.3.0-py3.6-linux-x86_64.egg/PIL/FitsStubImagePlugin.py
.eggs/Pillow-5.3.0-py3.6-linux-x86_64.egg/PIL/FliImagePlugin.py
.eggs/Pillow-5.3.0-py3.6-linux-x86_64.egg/PIL/FontFile.py
.eggs/Pillow-5.3.0-py3.6-linux-x86_64.egg/PIL/FpxImagePlugin.py
.eggs/Pillow-5.3.0-py3.6-linux-x86_64.egg/PIL/FtexImagePlugin.py
.eggs/Pillow-5.3.0-py3.6-linux-x86_64.egg/PIL/GbrImagePlugin.py
.eggs/Pillow-5.3.0-py3.6-linux-x86_64.egg/PIL/GdImageFile.py
.eggs/Pillow-5.3.0-py3.6-linux-x86_64.egg/PIL/GifImagePlugin.py
.eggs/Pillow-5.3.0-py3.6-linux-x86_64.egg/PIL/GimpGradientFile.py
.eggs/Pillow-5.3.0-py3.6-linux-x86_64.egg/PIL/GimpPaletteFile.py
.eggs/Pillow-5.3.0-py3.6-linux-x86_64.egg/PIL/GribStubImagePlugin.py
.eggs/Pillow-5.3.0-py3.6-linux-x86_64.egg/PIL/Hdf5StubImagePlugin.py
.eggs/Pillow-5.3.0-py3.6-linux-x86_64.egg/PIL/IcnsImagePlugin.py
.eggs/Pillow-5.3.0-py3.6-linux-x86_64.egg/PIL/IcoImagePlugin.py
.eggs/Pillow-5.3.0-py3.6-linux-x86_64.egg/PIL/ImImagePlugin.py
.eggs/Pillow-5.3.0-py3.6-linux-x86_64.egg/PIL/Image.py
.eggs/Pillow-5.3.0-py3.6-linux-x86_64.egg/PIL/ImageChops.py
.eggs/Pillow-5.3.0-py3.6-linux-x86_64.egg/PIL/ImageCms.py
.eggs/Pillow-5.3.0-py3.6-linux-x86_64.egg/PIL/ImageColor.py
.eggs/Pillow-5.3.0-py3.6-linux-x86_64.egg/PIL/ImageDraw.py
elcato.egg-info/PKG-INFO
elcato.egg-info/SOURCES.txt
elcato.egg-info/dependency_links.txt
elcato.egg-info/entry_points.txt
elcato.egg-info/requires.txt
elcato.egg-info/top_level.txt
