Metadata-Version: 1.1
Name: elcato
Version: 0.61
Summary: Static blog generator
Home-page: https://gitlab.com/python-open-source-library-collection/elcato
Author: Oliver Marks
Author-email: oly@digitaloctave.com
License:                     GNU GENERAL PUBLIC LICENSE
